{"operators": [{"envelope_generator": {"rates": [18, 24, 10, 17], "levels": [45, 99, 99, 0]}, "keyboard": {"level_scaling": {"break_point": 27, "left_depth": 0, "left_curve": "-LIN", "right_depth": 60, "right_curve": "-EXP"}, "rate_scaling": 7, "velocity_sensitivity": 0}, "oscillator": {"detune": 0, "frequency": {"fine": 0, "coarse": 0}, "mode": "fixed"}, "amp_mod_sensitivity": 0, "output_level": 90}, {"envelope_generator": {"rates": [11, 37, 37, 15], "levels": [82, 99, 92, 85]}, "keyboard": {"level_scaling": {"break_point": 27, "left_depth": 0, "left_curve": "-LIN", "right_depth": 45, "right_curve": "-EXP"}, "rate_scaling": 7, "velocity_sensitivity": 0}, "oscillator": {"detune": -4, "frequency": {"fine": 0, "coarse": 2}, "mode": "ratio"}, "amp_mod_sensitivity": 1, "output_level": 96}, {"envelope_generator": {"rates": [36, 46, 13, 29], "levels": [72, 99, 39, 0]}, "keyboard": {"level_scaling": {"break_point": 27, "left_depth": 0, "left_curve": "-LIN", "right_depth": 10, "right_curve": "-EXP"}, "rate_scaling": 7, "velocity_sensitivity": 0}, "oscillator": {"detune": -2, "frequency": {"fine": 0, "coarse": 6}, "mode": "ratio"}, "amp_mod_sensitivity": 0, "output_level": 72}, {"envelope_generator": {"rates": [99, 99, 0, 61], "levels": [83, 99, 0, 0]}, "keyboard": {"level_scaling": {"break_point": 27, "left_depth": 0, "left_curve": "-LIN", "right_depth": 0, "right_curve": "-EXP"}, "rate_scaling": 0, "velocity_sensitivity": 0}, "oscillator": {"detune": -1, "frequency": {"fine": 0, "coarse": 4}, "mode": "ratio"}, "amp_mod_sensitivity": 0, "output_level": 81}, {"envelope_generator": {"rates": [37, 24, 10, 23], "levels": [45, 99, 99, 0]}, "keyboard": {"level_scaling": {"break_point": 27, "left_depth": 14, "left_curve": "-LIN", "right_depth": 0, "right_curve": "-EXP"}, "rate_scaling": 7, "velocity_sensitivity": 3}, "oscillator": {"detune": -2, "frequency": {"fine": 0, "coarse": 2}, "mode": "ratio"}, "amp_mod_sensitivity": 0, "output_level": 88}, {"envelope_generator": {"rates": [35, 46, 13, 17], "levels": [72, 99, 39, 0]}, "keyboard": {"level_scaling": {"break_point": 27, "left_depth": 0, "left_curve": "-LIN", "right_depth": 21, "right_curve": "-EXP"}, "rate_scaling": 7, "velocity_sensitivity": 6}, "oscillator": {"detune": 0, "frequency": {"fine": 0, "coarse": 10}, "mode": "ratio"}, "amp_mod_sensitivity": 0, "output_level": 99}], "pitch_envelope_generator": {"rates": [99, 99, 99, 99], "levels": [50, 50, 50, 50]}, "algorithm": 16, "feedback": 2, "oscillator_key_sync": false, "lfo": {"speed": 74, "delay": 0, "pitch_mod_depth": 0, "amp_mod_depth": 0, "key_sync": false, "waveform": "sine"}, "pitch_mod_sensitivity": 2, "transpose": 0, "NAME": "XYZ 2", "MANUFACTURER": "yamaha", "MODEL": "dx7", "SIGNATURE": "1bcdad22af7e188e5f317f4eb5363a9cc2a63ab6", "AUTHOR": "_Unknown", "BANK": "SYNTH072.SYX"}