{"operators": [{"envelope_generator": {"rates": [99, 21, 99, 28], "levels": [99, 36, 44, 0]}, "keyboard": {"level_scaling": {"break_point": 0, "left_depth": 30, "left_curve": "-LIN", "right_depth": 0, "right_curve": "+EXP"}, "rate_scaling": 6, "velocity_sensitivity": 5}, "oscillator": {"detune": 6, "frequency": {"fine": 1, "coarse": 1}, "mode": "ratio"}, "amp_mod_sensitivity": 0, "output_level": 99}, {"envelope_generator": {"rates": [99, 28, 32, 32], "levels": [99, 58, 95, 0]}, "keyboard": {"level_scaling": {"break_point": 0, "left_depth": 64, "left_curve": "-LIN", "right_depth": 0, "right_curve": "+LIN"}, "rate_scaling": 0, "velocity_sensitivity": 4}, "oscillator": {"detune": 1, "frequency": {"fine": 1, "coarse": 1}, "mode": "ratio"}, "amp_mod_sensitivity": 0, "output_level": 76}, {"envelope_generator": {"rates": [66, 22, 42, 39], "levels": [99, 51, 53, 0]}, "keyboard": {"level_scaling": {"break_point": 23, "left_depth": 39, "left_curve": "-LIN", "right_depth": 0, "right_curve": "+LIN"}, "rate_scaling": 5, "velocity_sensitivity": 3}, "oscillator": {"detune": -7, "frequency": {"fine": 1, "coarse": 1}, "mode": "ratio"}, "amp_mod_sensitivity": 0, "output_level": 99}, {"envelope_generator": {"rates": [94, 23, 64, 53], "levels": [99, 51, 54, 0]}, "keyboard": {"level_scaling": {"break_point": 0, "left_depth": 48, "left_curve": "-LIN", "right_depth": 0, "right_curve": "-EXP"}, "rate_scaling": 2, "velocity_sensitivity": 4}, "oscillator": {"detune": 0, "frequency": {"fine": 0, "coarse": 2}, "mode": "ratio"}, "amp_mod_sensitivity": 0, "output_level": 71}, {"envelope_generator": {"rates": [95, 33, 49, 35], "levels": [99, 51, 54, 0]}, "keyboard": {"level_scaling": {"break_point": 0, "left_depth": 0, "left_curve": "-LIN", "right_depth": 0, "right_curve": "+LIN"}, "rate_scaling": 3, "velocity_sensitivity": 4}, "oscillator": {"detune": 0, "frequency": {"fine": 0, "coarse": 1}, "mode": "ratio"}, "amp_mod_sensitivity": 0, "output_level": 82}, {"envelope_generator": {"rates": [94, 44, 41, 46], "levels": [99, 63, 54, 0]}, "keyboard": {"level_scaling": {"break_point": 5, "left_depth": 0, "left_curve": "-LIN", "right_depth": 0, "right_curve": "+LIN"}, "rate_scaling": 1, "velocity_sensitivity": 0}, "oscillator": {"detune": 0, "frequency": {"fine": 0, "coarse": 4}, "mode": "ratio"}, "amp_mod_sensitivity": 0, "output_level": 79}], "pitch_envelope_generator": {"rates": [0, 0, 1, 0], "levels": [50, 50, 50, 50]}, "algorithm": 9, "feedback": 0, "oscillator_key_sync": true, "lfo": {"speed": 35, "delay": 39, "pitch_mod_depth": 0, "amp_mod_depth": 0, "key_sync": true, "waveform": "triangle"}, "pitch_mod_sensitivity": 3, "transpose": 24, "NAME": "OMPS TONE", "MANUFACTURER": "yamaha", "MODEL": "dx7", "SIGNATURE": "2e1c3dfe81cc9cfcd1d2cf6d8f6ebcb61c24cdc8", "AUTHOR": "_Unknown", "BANK": "CHRPER05.SYX"}