{"operators": [{"envelope_generator": {"rates": [81, 24, 18, 46], "levels": [99, 79, 0, 0]}, "keyboard": {"level_scaling": {"break_point": 30, "left_depth": 0, "left_curve": "-LIN", "right_depth": 0, "right_curve": "-LIN"}, "rate_scaling": 6, "velocity_sensitivity": 3}, "oscillator": {"detune": -7, "frequency": {"fine": 0, "coarse": 1}, "mode": "ratio"}, "amp_mod_sensitivity": 0, "output_level": 99}, {"envelope_generator": {"rates": [92, 94, 88, 52], "levels": [99, 65, 0, 0]}, "keyboard": {"level_scaling": {"break_point": 67, "left_depth": 29, "left_curve": "+LIN", "right_depth": 57, "right_curve": "-EXP"}, "rate_scaling": 6, "velocity_sensitivity": 1}, "oscillator": {"detune": 0, "frequency": {"fine": 87, "coarse": 1}, "mode": "fixed"}, "amp_mod_sensitivity": 3, "output_level": 87}, {"envelope_generator": {"rates": [83, 79, 58, 62], "levels": [99, 91, 0, 0]}, "keyboard": {"level_scaling": {"break_point": 75, "left_depth": 75, "left_curve": "+LIN", "right_depth": 78, "right_curve": "-LIN"}, "rate_scaling": 6, "velocity_sensitivity": 3}, "oscillator": {"detune": 0, "frequency": {"fine": 0, "coarse": 12}, "mode": "ratio"}, "amp_mod_sensitivity": 1, "output_level": 77}, {"envelope_generator": {"rates": [77, 43, 79, 32], "levels": [99, 31, 0, 0]}, "keyboard": {"level_scaling": {"break_point": 80, "left_depth": 0, "left_curve": "-LIN", "right_depth": 14, "right_curve": "-EXP"}, "rate_scaling": 4, "velocity_sensitivity": 3}, "oscillator": {"detune": 1, "frequency": {"fine": 0, "coarse": 11}, "mode": "ratio"}, "amp_mod_sensitivity": 1, "output_level": 77}, {"envelope_generator": {"rates": [20, 26, 56, 90], "levels": [99, 70, 0, 0]}, "keyboard": {"level_scaling": {"break_point": 4, "left_depth": 0, "left_curve": "-EXP", "right_depth": 96, "right_curve": "-LIN"}, "rate_scaling": 1, "velocity_sensitivity": 4}, "oscillator": {"detune": 2, "frequency": {"fine": 0, "coarse": 14}, "mode": "ratio"}, "amp_mod_sensitivity": 0, "output_level": 72}, {"envelope_generator": {"rates": [99, 7, 97, 31], "levels": [99, 54, 0, 0]}, "keyboard": {"level_scaling": {"break_point": 37, "left_depth": 0, "left_curve": "+EXP", "right_depth": 64, "right_curve": "-EXP"}, "rate_scaling": 5, "velocity_sensitivity": 0}, "oscillator": {"detune": 0, "frequency": {"fine": 0, "coarse": 5}, "mode": "ratio"}, "amp_mod_sensitivity": 0, "output_level": 58}], "pitch_envelope_generator": {"rates": [99, 99, 99, 99], "levels": [50, 50, 50, 50]}, "algorithm": 16, "feedback": 7, "oscillator_key_sync": false, "lfo": {"speed": 35, "delay": 0, "pitch_mod_depth": 3, "amp_mod_depth": 0, "key_sync": true, "waveform": "triangle"}, "pitch_mod_sensitivity": 3, "transpose": 24, "NAME": "BOSDORF /;", "MANUFACTURER": "yamaha", "MODEL": "dx7", "SIGNATURE": "63bc202b349aad6d61eb253cc3c289b73f064d58", "AUTHOR": "_Unknown", "BANK": "SYNTH056.SYX"}