{"operators": [{"envelope_generator": {"rates": [55, 22, 39, 93], "levels": [99, 99, 0, 0]}, "keyboard": {"level_scaling": {"break_point": 0, "left_depth": 0, "left_curve": "-LIN", "right_depth": 0, "right_curve": "-LIN"}, "rate_scaling": 0, "velocity_sensitivity": 0}, "oscillator": {"detune": -3, "frequency": {"fine": 0, "coarse": 2}, "mode": "ratio"}, "amp_mod_sensitivity": 0, "output_level": 89}, {"envelope_generator": {"rates": [70, 99, 70, 53], "levels": [99, 99, 20, 0]}, "keyboard": {"level_scaling": {"break_point": 0, "left_depth": 0, "left_curve": "-LIN", "right_depth": 0, "right_curve": "-LIN"}, "rate_scaling": 0, "velocity_sensitivity": 0}, "oscillator": {"detune": 3, "frequency": {"fine": 0, "coarse": 7}, "mode": "ratio"}, "amp_mod_sensitivity": 0, "output_level": 99}, {"envelope_generator": {"rates": [55, 32, 52, 99], "levels": [99, 99, 0, 0]}, "keyboard": {"level_scaling": {"break_point": 0, "left_depth": 0, "left_curve": "-LIN", "right_depth": 0, "right_curve": "-LIN"}, "rate_scaling": 0, "velocity_sensitivity": 0}, "oscillator": {"detune": -7, "frequency": {"fine": 0, "coarse": 1}, "mode": "ratio"}, "amp_mod_sensitivity": 0, "output_level": 99}, {"envelope_generator": {"rates": [70, 99, 70, 33], "levels": [99, 99, 0, 0]}, "keyboard": {"level_scaling": {"break_point": 0, "left_depth": 0, "left_curve": "-LIN", "right_depth": 0, "right_curve": "-LIN"}, "rate_scaling": 0, "velocity_sensitivity": 0}, "oscillator": {"detune": 7, "frequency": {"fine": 0, "coarse": 5}, "mode": "ratio"}, "amp_mod_sensitivity": 0, "output_level": 99}, {"envelope_generator": {"rates": [44, 40, 40, 45], "levels": [99, 99, 0, 0]}, "keyboard": {"level_scaling": {"break_point": 42, "left_depth": 23, "left_curve": "-LIN", "right_depth": 0, "right_curve": "-LIN"}, "rate_scaling": 3, "velocity_sensitivity": 2}, "oscillator": {"detune": 5, "frequency": {"fine": 0, "coarse": 1}, "mode": "ratio"}, "amp_mod_sensitivity": 0, "output_level": 84}, {"envelope_generator": {"rates": [99, 99, 45, 39], "levels": [99, 99, 29, 0]}, "keyboard": {"level_scaling": {"break_point": 0, "left_depth": 0, "left_curve": "-LIN", "right_depth": 0, "right_curve": "-LIN"}, "rate_scaling": 3, "velocity_sensitivity": 3}, "oscillator": {"detune": -5, "frequency": {"fine": 0, "coarse": 10}, "mode": "ratio"}, "amp_mod_sensitivity": 0, "output_level": 85}], "pitch_envelope_generator": {"rates": [99, 99, 99, 99], "levels": [50, 50, 50, 50]}, "algorithm": 6, "feedback": 0, "oscillator_key_sync": true, "lfo": {"speed": 35, "delay": 0, "pitch_mod_depth": 0, "amp_mod_depth": 0, "key_sync": true, "waveform": "triangle"}, "pitch_mod_sensitivity": 3, "transpose": 24, "NAME": "SAMPLER", "MANUFACTURER": "yamaha", "MODEL": "dx7", "SIGNATURE": "988678ba40cd37696ba585809ce8c1519003002f", "AUTHOR": "Big Mamma", "BANK": "BIGMAMMA259.SYX"}