{"operators": [{"envelope_generator": {"rates": [99, 25, 20, 47], "levels": [99, 62, 0, 0]}, "keyboard": {"level_scaling": {"break_point": 39, "left_depth": 0, "left_curve": "-LIN", "right_depth": 99, "right_curve": "+LIN"}, "rate_scaling": 3, "velocity_sensitivity": 5}, "oscillator": {"detune": 0, "frequency": {"fine": 0, "coarse": 1}, "mode": "ratio"}, "amp_mod_sensitivity": 0, "output_level": 99}, {"envelope_generator": {"rates": [99, 15, 25, 47], "levels": [99, 75, 0, 0]}, "keyboard": {"level_scaling": {"break_point": 55, "left_depth": 0, "left_curve": "-LIN", "right_depth": 44, "right_curve": "-LIN"}, "rate_scaling": 4, "velocity_sensitivity": 6}, "oscillator": {"detune": 0, "frequency": {"fine": 0, "coarse": 1}, "mode": "ratio"}, "amp_mod_sensitivity": 0, "output_level": 90}, {"envelope_generator": {"rates": [90, 30, 30, 50], "levels": [99, 85, 0, 0]}, "keyboard": {"level_scaling": {"break_point": 46, "left_depth": 20, "left_curve": "+LIN", "right_depth": 65, "right_curve": "-LIN"}, "rate_scaling": 4, "velocity_sensitivity": 6}, "oscillator": {"detune": 1, "frequency": {"fine": 0, "coarse": 3}, "mode": "ratio"}, "amp_mod_sensitivity": 0, "output_level": 80}, {"envelope_generator": {"rates": [99, 30, 30, 25], "levels": [99, 50, 0, 50]}, "keyboard": {"level_scaling": {"break_point": 39, "left_depth": 0, "left_curve": "-LIN", "right_depth": 90, "right_curve": "-LIN"}, "rate_scaling": 4, "velocity_sensitivity": 7}, "oscillator": {"detune": 1, "frequency": {"fine": 0, "coarse": 6}, "mode": "ratio"}, "amp_mod_sensitivity": 0, "output_level": 82}, {"envelope_generator": {"rates": [90, 30, 30, 50], "levels": [99, 85, 0, 0]}, "keyboard": {"level_scaling": {"break_point": 46, "left_depth": 0, "left_curve": "+LIN", "right_depth": 65, "right_curve": "-LIN"}, "rate_scaling": 4, "velocity_sensitivity": 5}, "oscillator": {"detune": 0, "frequency": {"fine": 0, "coarse": 8}, "mode": "ratio"}, "amp_mod_sensitivity": 0, "output_level": 60}, {"envelope_generator": {"rates": [90, 30, 30, 50], "levels": [99, 85, 0, 0]}, "keyboard": {"level_scaling": {"break_point": 46, "left_depth": 20, "left_curve": "+LIN", "right_depth": 65, "right_curve": "-LIN"}, "rate_scaling": 4, "velocity_sensitivity": 6}, "oscillator": {"detune": 0, "frequency": {"fine": 0, "coarse": 2}, "mode": "ratio"}, "amp_mod_sensitivity": 0, "output_level": 69}], "pitch_envelope_generator": {"rates": [94, 67, 95, 60], "levels": [50, 50, 50, 50]}, "algorithm": 18, "feedback": 0, "oscillator_key_sync": false, "lfo": {"speed": 30, "delay": 0, "pitch_mod_depth": 0, "amp_mod_depth": 0, "key_sync": false, "waveform": "triangle"}, "pitch_mod_sensitivity": 0, "transpose": 24, "NAME": "VLEUGEL  1", "MANUFACTURER": "yamaha", "MODEL": "dx7", "SIGNATURE": "9a66871d80d82747bd4553a7779fe9710fb4cf81", "AUTHOR": "Yamaha", "BANK": "YAMAHA01.SYX"}