{"operators": [{"envelope_generator": {"rates": [96, 23, 25, 54], "levels": [99, 75, 0, 0]}, "keyboard": {"level_scaling": {"break_point": 49, "left_depth": 0, "left_curve": "-LIN", "right_depth": 0, "right_curve": "-LIN"}, "rate_scaling": 7, "velocity_sensitivity": 0}, "oscillator": {"detune": 0, "frequency": {"fine": 0, "coarse": 1}, "mode": "ratio"}, "amp_mod_sensitivity": 0, "output_level": 95}, {"envelope_generator": {"rates": [95, 99, 0, 54], "levels": [99, 99, 75, 0]}, "keyboard": {"level_scaling": {"break_point": 49, "left_depth": 0, "left_curve": "-LIN", "right_depth": 0, "right_curve": "-LIN"}, "rate_scaling": 7, "velocity_sensitivity": 0}, "oscillator": {"detune": 0, "frequency": {"fine": 0, "coarse": 1}, "mode": "ratio"}, "amp_mod_sensitivity": 1, "output_level": 76}, {"envelope_generator": {"rates": [95, 27, 20, 54], "levels": [99, 80, 0, 0]}, "keyboard": {"level_scaling": {"break_point": 36, "left_depth": 36, "left_curve": "-LIN", "right_depth": 0, "right_curve": "-LIN"}, "rate_scaling": 4, "velocity_sensitivity": 2}, "oscillator": {"detune": 7, "frequency": {"fine": 0, "coarse": 4}, "mode": "ratio"}, "amp_mod_sensitivity": 0, "output_level": 94}, {"envelope_generator": {"rates": [97, 41, 13, 54], "levels": [99, 81, 0, 0]}, "keyboard": {"level_scaling": {"break_point": 49, "left_depth": 0, "left_curve": "-LIN", "right_depth": 0, "right_curve": "-LIN"}, "rate_scaling": 0, "velocity_sensitivity": 0}, "oscillator": {"detune": 0, "frequency": {"fine": 0, "coarse": 14}, "mode": "ratio"}, "amp_mod_sensitivity": 0, "output_level": 42}, {"envelope_generator": {"rates": [72, 78, 20, 57], "levels": [99, 99, 99, 0]}, "keyboard": {"level_scaling": {"break_point": 49, "left_depth": 0, "left_curve": "-LIN", "right_depth": 0, "right_curve": "-LIN"}, "rate_scaling": 5, "velocity_sensitivity": 0}, "oscillator": {"detune": 0, "frequency": {"fine": 0, "coarse": 1}, "mode": "ratio"}, "amp_mod_sensitivity": 1, "output_level": 99}, {"envelope_generator": {"rates": [51, 52, 25, 54], "levels": [98, 99, 98, 0]}, "keyboard": {"level_scaling": {"break_point": 7, "left_depth": 0, "left_curve": "-LIN", "right_depth": 0, "right_curve": "-LIN"}, "rate_scaling": 4, "velocity_sensitivity": 0}, "oscillator": {"detune": 0, "frequency": {"fine": 0, "coarse": 1}, "mode": "ratio"}, "amp_mod_sensitivity": 1, "output_level": 78}], "pitch_envelope_generator": {"rates": [94, 67, 95, 60], "levels": [50, 50, 50, 50]}, "algorithm": 5, "feedback": 7, "oscillator_key_sync": false, "lfo": {"speed": 46, "delay": 0, "pitch_mod_depth": 0, "amp_mod_depth": 0, "key_sync": true, "waveform": "sine"}, "pitch_mod_sensitivity": 0, "transpose": 12, "NAME": "PNO-BRS FT", "MANUFACTURER": "yamaha", "MODEL": "dx7", "SIGNATURE": "97e5a442b88b51996e0af258f3104f8765acb58b", "AUTHOR": "_Unknown", "BANK": "STEVE1.SYX"}