{"operators": [{"envelope_generator": {"rates": [72, 99, 26, 42], "levels": [99, 99, 0, 0]}, "keyboard": {"level_scaling": {"break_point": 51, "left_depth": 75, "left_curve": "+LIN", "right_depth": 46, "right_curve": "+LIN"}, "rate_scaling": 0, "velocity_sensitivity": 0}, "oscillator": {"detune": 0, "frequency": {"fine": 0, "coarse": 0}, "mode": "ratio"}, "amp_mod_sensitivity": 0, "output_level": 99}, {"envelope_generator": {"rates": [99, 99, 0, 36], "levels": [99, 99, 0, 0]}, "keyboard": {"level_scaling": {"break_point": 49, "left_depth": 0, "left_curve": "-LIN", "right_depth": 12, "right_curve": "+EXP"}, "rate_scaling": 7, "velocity_sensitivity": 0}, "oscillator": {"detune": 0, "frequency": {"fine": 35, "coarse": 4}, "mode": "fixed"}, "amp_mod_sensitivity": 0, "output_level": 76}, {"envelope_generator": {"rates": [90, 60, 40, 21], "levels": [99, 71, 8, 0]}, "keyboard": {"level_scaling": {"break_point": 51, "left_depth": 0, "left_curve": "-LIN", "right_depth": 2, "right_curve": "+LIN"}, "rate_scaling": 2, "velocity_sensitivity": 5}, "oscillator": {"detune": 0, "frequency": {"fine": 0, "coarse": 3}, "mode": "ratio"}, "amp_mod_sensitivity": 0, "output_level": 99}, {"envelope_generator": {"rates": [99, 48, 20, 23], "levels": [99, 99, 99, 0]}, "keyboard": {"level_scaling": {"break_point": 54, "left_depth": 47, "left_curve": "-LIN", "right_depth": 14, "right_curve": "+EXP"}, "rate_scaling": 3, "velocity_sensitivity": 0}, "oscillator": {"detune": 0, "frequency": {"fine": 0, "coarse": 1}, "mode": "ratio"}, "amp_mod_sensitivity": 0, "output_level": 88}, {"envelope_generator": {"rates": [99, 99, 0, 33], "levels": [99, 99, 0, 0]}, "keyboard": {"level_scaling": {"break_point": 56, "left_depth": 37, "left_curve": "-LIN", "right_depth": 0, "right_curve": "+EXP"}, "rate_scaling": 3, "velocity_sensitivity": 0}, "oscillator": {"detune": 0, "frequency": {"fine": 54, "coarse": 12}, "mode": "fixed"}, "amp_mod_sensitivity": 0, "output_level": 70}, {"envelope_generator": {"rates": [99, 54, 28, 21], "levels": [99, 85, 52, 0]}, "keyboard": {"level_scaling": {"break_point": 46, "left_depth": 41, "left_curve": "-LIN", "right_depth": 9, "right_curve": "+LIN"}, "rate_scaling": 4, "velocity_sensitivity": 0}, "oscillator": {"detune": 0, "frequency": {"fine": 0, "coarse": 17}, "mode": "ratio"}, "amp_mod_sensitivity": 0, "output_level": 78}], "pitch_envelope_generator": {"rates": [51, 47, 0, 46], "levels": [0, 0, 99, 81]}, "algorithm": 3, "feedback": 7, "oscillator_key_sync": true, "lfo": {"speed": 35, "delay": 0, "pitch_mod_depth": 0, "amp_mod_depth": 0, "key_sync": true, "waveform": "triangle"}, "pitch_mod_sensitivity": 3, "transpose": 36, "NAME": "Weird", "MANUFACTURER": "yamaha", "MODEL": "dx7", "SIGNATURE": "d1b9d1d9de093626a20c22a918dc5d44dd6a34f4", "AUTHOR": "Tim Garrett", "BANK": "TX7-94B.SYX", "SOURCE": "http://www.recup.ch/banques_dx7.htm"}