{"operators": [{"envelope_generator": {"rates": [99, 32, 50, 46], "levels": [99, 80, 0, 0]}, "keyboard": {"level_scaling": {"break_point": 15, "left_depth": 0, "left_curve": "-LIN", "right_depth": 20, "right_curve": "-EXP"}, "rate_scaling": 3, "velocity_sensitivity": 0}, "oscillator": {"detune": 0, "frequency": {"fine": 0, "coarse": 1}, "mode": "ratio"}, "amp_mod_sensitivity": 0, "output_level": 98}, {"envelope_generator": {"rates": [99, 62, 55, 50], "levels": [99, 80, 0, 0]}, "keyboard": {"level_scaling": {"break_point": 15, "left_depth": 0, "left_curve": "-LIN", "right_depth": 20, "right_curve": "-EXP"}, "rate_scaling": 4, "velocity_sensitivity": 0}, "oscillator": {"detune": 1, "frequency": {"fine": 0, "coarse": 7}, "mode": "ratio"}, "amp_mod_sensitivity": 0, "output_level": 68}, {"envelope_generator": {"rates": [98, 10, 43, 61], "levels": [96, 0, 1, 0]}, "keyboard": {"level_scaling": {"break_point": 46, "left_depth": 0, "left_curve": "-LIN", "right_depth": 99, "right_curve": "-LIN"}, "rate_scaling": 0, "velocity_sensitivity": 0}, "oscillator": {"detune": -1, "frequency": {"fine": 0, "coarse": 1}, "mode": "ratio"}, "amp_mod_sensitivity": 3, "output_level": 90}, {"envelope_generator": {"rates": [98, 11, 43, 61], "levels": [96, 0, 1, 0]}, "keyboard": {"level_scaling": {"break_point": 43, "left_depth": 0, "left_curve": "-LIN", "right_depth": 99, "right_curve": "-LIN"}, "rate_scaling": 0, "velocity_sensitivity": 0}, "oscillator": {"detune": 4, "frequency": {"fine": 0, "coarse": 1}, "mode": "ratio"}, "amp_mod_sensitivity": 3, "output_level": 97}, {"envelope_generator": {"rates": [98, 11, 43, 61], "levels": [96, 0, 1, 0]}, "keyboard": {"level_scaling": {"break_point": 15, "left_depth": 0, "left_curve": "-LIN", "right_depth": 94, "right_curve": "-EXP"}, "rate_scaling": 0, "velocity_sensitivity": 0}, "oscillator": {"detune": -7, "frequency": {"fine": 51, "coarse": 4}, "mode": "ratio"}, "amp_mod_sensitivity": 2, "output_level": 84}, {"envelope_generator": {"rates": [98, 11, 43, 61], "levels": [96, 0, 1, 0]}, "keyboard": {"level_scaling": {"break_point": 43, "left_depth": 0, "left_curve": "-LIN", "right_depth": 99, "right_curve": "-LIN"}, "rate_scaling": 7, "velocity_sensitivity": 0}, "oscillator": {"detune": 4, "frequency": {"fine": 25, "coarse": 6}, "mode": "ratio"}, "amp_mod_sensitivity": 2, "output_level": 66}], "pitch_envelope_generator": {"rates": [99, 99, 99, 99], "levels": [51, 50, 50, 50]}, "algorithm": 9, "feedback": 7, "oscillator_key_sync": true, "lfo": {"speed": 40, "delay": 79, "pitch_mod_depth": 0, "amp_mod_depth": 0, "key_sync": false, "waveform": "triangle"}, "pitch_mod_sensitivity": 0, "transpose": 24, "NAME": "Mtl/Marimb", "MANUFACTURER": "yamaha", "MODEL": "dx7", "SIGNATURE": "90fc92f8ecc86bf37b3fc14456dfa0f7107f48e4", "AUTHOR": "Tim Garrett", "BANK": "TX7-48C.SYX"}