{"operators": [{"envelope_generator": {"rates": [99, 99, 99, 85], "levels": [99, 99, 99, 0]}, "keyboard": {"level_scaling": {"break_point": 0, "left_depth": 0, "left_curve": "-LIN", "right_depth": 0, "right_curve": "-LIN"}, "rate_scaling": 0, "velocity_sensitivity": 0}, "oscillator": {"detune": -6, "frequency": {"fine": 0, "coarse": 4}, "mode": "fixed"}, "amp_mod_sensitivity": 0, "output_level": 99}, {"envelope_generator": {"rates": [99, 75, 99, 41], "levels": [99, 88, 86, 0]}, "keyboard": {"level_scaling": {"break_point": 39, "left_depth": 73, "left_curve": "+EXP", "right_depth": 1, "right_curve": "-LIN"}, "rate_scaling": 0, "velocity_sensitivity": 4}, "oscillator": {"detune": 7, "frequency": {"fine": 0, "coarse": 1}, "mode": "ratio"}, "amp_mod_sensitivity": 0, "output_level": 96}, {"envelope_generator": {"rates": [95, 85, 80, 59], "levels": [99, 66, 95, 0]}, "keyboard": {"level_scaling": {"break_point": 0, "left_depth": 0, "left_curve": "-LIN", "right_depth": 0, "right_curve": "-LIN"}, "rate_scaling": 0, "velocity_sensitivity": 0}, "oscillator": {"detune": 1, "frequency": {"fine": 28, "coarse": 0}, "mode": "fixed"}, "amp_mod_sensitivity": 0, "output_level": 99}, {"envelope_generator": {"rates": [90, 79, 56, 79], "levels": [99, 81, 0, 0]}, "keyboard": {"level_scaling": {"break_point": 0, "left_depth": 0, "left_curve": "-LIN", "right_depth": 0, "right_curve": "-LIN"}, "rate_scaling": 4, "velocity_sensitivity": 4}, "oscillator": {"detune": 3, "frequency": {"fine": 0, "coarse": 3}, "mode": "ratio"}, "amp_mod_sensitivity": 0, "output_level": 87}, {"envelope_generator": {"rates": [99, 60, 71, 60], "levels": [99, 85, 90, 0]}, "keyboard": {"level_scaling": {"break_point": 0, "left_depth": 0, "left_curve": "-LIN", "right_depth": 0, "right_curve": "-LIN"}, "rate_scaling": 0, "velocity_sensitivity": 6}, "oscillator": {"detune": 0, "frequency": {"fine": 0, "coarse": 6}, "mode": "ratio"}, "amp_mod_sensitivity": 3, "output_level": 66}, {"envelope_generator": {"rates": [99, 99, 55, 71], "levels": [99, 99, 97, 0]}, "keyboard": {"level_scaling": {"break_point": 36, "left_depth": 0, "left_curve": "-LIN", "right_depth": 99, "right_curve": "-EXP"}, "rate_scaling": 0, "velocity_sensitivity": 0}, "oscillator": {"detune": 7, "frequency": {"fine": 65, "coarse": 8}, "mode": "fixed"}, "amp_mod_sensitivity": 3, "output_level": 55}], "pitch_envelope_generator": {"rates": [99, 99, 99, 99], "levels": [50, 50, 50, 50]}, "algorithm": 12, "feedback": 0, "oscillator_key_sync": false, "lfo": {"speed": 60, "delay": 0, "pitch_mod_depth": 1, "amp_mod_depth": 0, "key_sync": true, "waveform": "triangle"}, "pitch_mod_sensitivity": 7, "transpose": 12, "NAME": "TOTO HMND1", "MANUFACTURER": "yamaha", "MODEL": "dx7", "SIGNATURE": "3ab598aec6a35aa23ee7569cb0214629be5236fc", "AUTHOR": "Aminet", "BANK": "159.syx", "SOURCE": "http://aminet.net/package/mus/midi/dx-syx"}