{"operators": [{"envelope_generator": {"rates": [99, 45, 24, 34], "levels": [99, 99, 0, 0]}, "keyboard": {"level_scaling": {"break_point": 32, "left_depth": 0, "left_curve": "-LIN", "right_depth": 0, "right_curve": "-LIN"}, "rate_scaling": 3, "velocity_sensitivity": 1}, "oscillator": {"detune": -7, "frequency": {"fine": 0, "coarse": 1}, "mode": "ratio"}, "amp_mod_sensitivity": 0, "output_level": 87}, {"envelope_generator": {"rates": [99, 50, 22, 20], "levels": [99, 93, 0, 0]}, "keyboard": {"level_scaling": {"break_point": 32, "left_depth": 0, "left_curve": "-LIN", "right_depth": 0, "right_curve": "-LIN"}, "rate_scaling": 3, "velocity_sensitivity": 0}, "oscillator": {"detune": 0, "frequency": {"fine": 0, "coarse": 4}, "mode": "ratio"}, "amp_mod_sensitivity": 0, "output_level": 82}, {"envelope_generator": {"rates": [85, 42, 25, 12], "levels": [85, 80, 0, 127]}, "keyboard": {"level_scaling": {"break_point": 32, "left_depth": 0, "left_curve": "-LIN", "right_depth": 0, "right_curve": "-LIN"}, "rate_scaling": 3, "velocity_sensitivity": 0}, "oscillator": {"detune": 4, "frequency": {"fine": 0, "coarse": 1}, "mode": "ratio"}, "amp_mod_sensitivity": 0, "output_level": 83}, {"envelope_generator": {"rates": [99, 45, 24, 31], "levels": [99, 95, 0, 0]}, "keyboard": {"level_scaling": {"break_point": 32, "left_depth": 0, "left_curve": "-LIN", "right_depth": 0, "right_curve": "-LIN"}, "rate_scaling": 3, "velocity_sensitivity": 0}, "oscillator": {"detune": 0, "frequency": {"fine": 0, "coarse": 1}, "mode": "ratio"}, "amp_mod_sensitivity": 0, "output_level": 99}, {"envelope_generator": {"rates": [99, 45, 24, 34], "levels": [99, 95, 0, 0]}, "keyboard": {"level_scaling": {"break_point": 32, "left_depth": 0, "left_curve": "-LIN", "right_depth": 0, "right_curve": "-LIN"}, "rate_scaling": 3, "velocity_sensitivity": 0}, "oscillator": {"detune": 0, "frequency": {"fine": 0, "coarse": 2}, "mode": "ratio"}, "amp_mod_sensitivity": 0, "output_level": 85}, {"envelope_generator": {"rates": [97, 82, 0, 0], "levels": [99, 85, 0, 0]}, "keyboard": {"level_scaling": {"break_point": 32, "left_depth": 0, "left_curve": "-LIN", "right_depth": 0, "right_curve": "-LIN"}, "rate_scaling": 3, "velocity_sensitivity": 1}, "oscillator": {"detune": 0, "frequency": {"fine": 0, "coarse": 1}, "mode": "ratio"}, "amp_mod_sensitivity": 0, "output_level": 97}], "pitch_envelope_generator": {"rates": [0, 0, 0, 0], "levels": [50, 50, 50, 50]}, "algorithm": 19, "feedback": 3, "oscillator_key_sync": true, "lfo": {"speed": 0, "delay": 0, "pitch_mod_depth": 0, "amp_mod_depth": 0, "key_sync": false, "waveform": "triangle"}, "pitch_mod_sensitivity": 0, "transpose": 24, "NAME": "CIMBAL", "MANUFACTURER": "yamaha", "MODEL": "dx7", "SIGNATURE": "f2058ddec78932b96715b59fc3db0d78e8bab97a", "AUTHOR": "_Unknown", "BANK": "DRUMS02.SYX"}