{"operators": [{"envelope_generator": {"rates": [95, 39, 39, 39], "levels": [99, 39, 0, 0]}, "keyboard": {"level_scaling": {"break_point": 23, "left_depth": 0, "left_curve": "-LIN", "right_depth": 99, "right_curve": "-LIN"}, "rate_scaling": 0, "velocity_sensitivity": 0}, "oscillator": {"detune": 0, "frequency": {"fine": 0, "coarse": 16}, "mode": "ratio"}, "amp_mod_sensitivity": 0, "output_level": 99}, {"envelope_generator": {"rates": [95, 39, 39, 39], "levels": [99, 39, 0, 0]}, "keyboard": {"level_scaling": {"break_point": 35, "left_depth": 90, "left_curve": "-LIN", "right_depth": 99, "right_curve": "-LIN"}, "rate_scaling": 0, "velocity_sensitivity": 0}, "oscillator": {"detune": 0, "frequency": {"fine": 0, "coarse": 8}, "mode": "ratio"}, "amp_mod_sensitivity": 0, "output_level": 99}, {"envelope_generator": {"rates": [95, 39, 39, 39], "levels": [99, 39, 0, 0]}, "keyboard": {"level_scaling": {"break_point": 46, "left_depth": 99, "left_curve": "-LIN", "right_depth": 99, "right_curve": "-LIN"}, "rate_scaling": 0, "velocity_sensitivity": 0}, "oscillator": {"detune": 0, "frequency": {"fine": 0, "coarse": 4}, "mode": "ratio"}, "amp_mod_sensitivity": 0, "output_level": 99}, {"envelope_generator": {"rates": [95, 39, 39, 39], "levels": [99, 39, 0, 0]}, "keyboard": {"level_scaling": {"break_point": 58, "left_depth": 99, "left_curve": "-LIN", "right_depth": 99, "right_curve": "-LIN"}, "rate_scaling": 0, "velocity_sensitivity": 0}, "oscillator": {"detune": 0, "frequency": {"fine": 0, "coarse": 2}, "mode": "ratio"}, "amp_mod_sensitivity": 0, "output_level": 99}, {"envelope_generator": {"rates": [95, 39, 39, 39], "levels": [99, 39, 0, 0]}, "keyboard": {"level_scaling": {"break_point": 75, "left_depth": 99, "left_curve": "-LIN", "right_depth": 0, "right_curve": "-LIN"}, "rate_scaling": 0, "velocity_sensitivity": 0}, "oscillator": {"detune": 0, "frequency": {"fine": 0, "coarse": 1}, "mode": "ratio"}, "amp_mod_sensitivity": 0, "output_level": 99}, {"envelope_generator": {"rates": [95, 39, 39, 39], "levels": [99, 39, 0, 0]}, "keyboard": {"level_scaling": {"break_point": 0, "left_depth": 0, "left_curve": "-LIN", "right_depth": 0, "right_curve": "-LIN"}, "rate_scaling": 0, "velocity_sensitivity": 0}, "oscillator": {"detune": 0, "frequency": {"fine": 0, "coarse": 21}, "mode": "ratio"}, "amp_mod_sensitivity": 0, "output_level": 61}], "pitch_envelope_generator": {"rates": [99, 99, 99, 99], "levels": [50, 50, 50, 50]}, "algorithm": 24, "feedback": 0, "oscillator_key_sync": true, "lfo": {"speed": 35, "delay": 0, "pitch_mod_depth": 0, "amp_mod_depth": 0, "key_sync": true, "waveform": "triangle"}, "pitch_mod_sensitivity": 3, "transpose": 24, "NAME": "playAscale", "MANUFACTURER": "yamaha", "MODEL": "dx7", "SIGNATURE": "8f84e86cead8a8972af112c7540a504e69be9cd2", "AUTHOR": "Tim Conrardy", "BANK": "AFTER.SYX"}