{"operators": [{"envelope_generator": {"rates": [80, 56, 10, 127], "levels": [98, 98, 36, 0]}, "keyboard": {"level_scaling": {"break_point": 0, "left_depth": 0, "left_curve": "-LIN", "right_depth": 0, "right_curve": "-LIN"}, "rate_scaling": 0, "velocity_sensitivity": 0}, "oscillator": {"detune": 0, "frequency": {"fine": 0, "coarse": 1}, "mode": "ratio"}, "amp_mod_sensitivity": 0, "output_level": 99}, {"envelope_generator": {"rates": [53, 46, 32, 54], "levels": [99, 93, 90, 0]}, "keyboard": {"level_scaling": {"break_point": 0, "left_depth": 0, "left_curve": "-LIN", "right_depth": 0, "right_curve": "-LIN"}, "rate_scaling": 0, "velocity_sensitivity": 0}, "oscillator": {"detune": -7, "frequency": {"fine": 0, "coarse": 1}, "mode": "ratio"}, "amp_mod_sensitivity": 0, "output_level": 83}, {"envelope_generator": {"rates": [54, 15, 10, 75], "levels": [99, 92, 0, 0]}, "keyboard": {"level_scaling": {"break_point": 0, "left_depth": 0, "left_curve": "-LIN", "right_depth": 0, "right_curve": "-LIN"}, "rate_scaling": 0, "velocity_sensitivity": 0}, "oscillator": {"detune": 7, "frequency": {"fine": 0, "coarse": 1}, "mode": "ratio"}, "amp_mod_sensitivity": 0, "output_level": 96}, {"envelope_generator": {"rates": [56, 74, 10, 99], "levels": [98, 98, 36, 0]}, "keyboard": {"level_scaling": {"break_point": 0, "left_depth": 0, "left_curve": "-LIN", "right_depth": 0, "right_curve": "-LIN"}, "rate_scaling": 0, "velocity_sensitivity": 0}, "oscillator": {"detune": 0, "frequency": {"fine": 0, "coarse": 1}, "mode": "ratio"}, "amp_mod_sensitivity": 0, "output_level": 73}, {"envelope_generator": {"rates": [76, 73, 10, 64], "levels": [99, 92, 0, 0]}, "keyboard": {"level_scaling": {"break_point": 0, "left_depth": 0, "left_curve": "-LIN", "right_depth": 0, "right_curve": "-LIN"}, "rate_scaling": 0, "velocity_sensitivity": 0}, "oscillator": {"detune": 0, "frequency": {"fine": 0, "coarse": 1}, "mode": "ratio"}, "amp_mod_sensitivity": 0, "output_level": 83}, {"envelope_generator": {"rates": [72, 76, 10, 70], "levels": [99, 92, 0, 0]}, "keyboard": {"level_scaling": {"break_point": 0, "left_depth": 0, "left_curve": "-LIN", "right_depth": 0, "right_curve": "-LIN"}, "rate_scaling": 0, "velocity_sensitivity": 0}, "oscillator": {"detune": 1, "frequency": {"fine": 0, "coarse": 1}, "mode": "ratio"}, "amp_mod_sensitivity": 0, "output_level": 127}], "pitch_envelope_generator": {"rates": [84, 95, 95, 60], "levels": [50, 50, 50, 50]}, "algorithm": 2, "feedback": 7, "oscillator_key_sync": true, "lfo": {"speed": 24, "delay": 38, "pitch_mod_depth": 2, "amp_mod_depth": 0, "key_sync": false, "waveform": "sine"}, "pitch_mod_sensitivity": 3, "transpose": 12, "NAME": "FANFARE  A", "MANUFACTURER": "yamaha", "MODEL": "dx7", "SIGNATURE": "94b4f1762248093742bcd556e2207f7d4e2ea9a8", "AUTHOR": "_Unknown", "BANK": "BRASS009.SYX"}