{"operators": [{"envelope_generator": {"rates": [80, 39, 32, 71], "levels": [99, 98, 80, 0]}, "keyboard": {"level_scaling": {"break_point": 51, "left_depth": 0, "left_curve": "-EXP", "right_depth": 0, "right_curve": "-EXP"}, "rate_scaling": 0, "velocity_sensitivity": 0}, "oscillator": {"detune": -7, "frequency": {"fine": 24, "coarse": 28}, "mode": "fixed"}, "amp_mod_sensitivity": 0, "output_level": 0}, {"envelope_generator": {"rates": [0, 80, 39, 32], "levels": [71, 99, 98, 80]}, "keyboard": {"level_scaling": {"break_point": 0, "left_depth": 51, "left_curve": "-LIN", "right_depth": 0, "right_curve": "-LIN"}, "rate_scaling": 0, "velocity_sensitivity": 0}, "oscillator": {"detune": 0, "frequency": {"fine": 0, "coarse": 0}, "mode": "ratio"}, "amp_mod_sensitivity": 0, "output_level": 25}, {"envelope_generator": {"rates": [80, 39, 32, 71], "levels": [99, 98, 80, 0]}, "keyboard": {"level_scaling": {"break_point": 51, "left_depth": 0, "left_curve": "+LIN", "right_depth": 0, "right_curve": "+LIN"}, "rate_scaling": 0, "velocity_sensitivity": 6}, "oscillator": {"detune": 0, "frequency": {"fine": 0, "coarse": 12}, "mode": "fixed"}, "amp_mod_sensitivity": 0, "output_level": 0}, {"envelope_generator": {"rates": [0, 80, 39, 32], "levels": [71, 99, 98, 80]}, "keyboard": {"level_scaling": {"break_point": 0, "left_depth": 51, "left_curve": "-LIN", "right_depth": 0, "right_curve": "-LIN"}, "rate_scaling": 7, "velocity_sensitivity": 6}, "oscillator": {"detune": -6, "frequency": {"fine": 0, "coarse": 1}, "mode": "ratio"}, "amp_mod_sensitivity": 0, "output_level": 99}, {"envelope_generator": {"rates": [80, 39, 32, 71], "levels": [99, 98, 80, 0]}, "keyboard": {"level_scaling": {"break_point": 51, "left_depth": 0, "left_curve": "+LIN", "right_depth": 0, "right_curve": "+LIN"}, "rate_scaling": 0, "velocity_sensitivity": 0}, "oscillator": {"detune": 0, "frequency": {"fine": 2, "coarse": 17}, "mode": "fixed"}, "amp_mod_sensitivity": 0, "output_level": 99}, {"envelope_generator": {"rates": [0, 80, 39, 32], "levels": [71, 99, 98, 80]}, "keyboard": {"level_scaling": {"break_point": 0, "left_depth": 51, "left_curve": "-LIN", "right_depth": 0, "right_curve": "-LIN"}, "rate_scaling": 7, "velocity_sensitivity": 6}, "oscillator": {"detune": -6, "frequency": {"fine": 0, "coarse": 17}, "mode": "fixed"}, "amp_mod_sensitivity": 0, "output_level": 0}], "pitch_envelope_generator": {"rates": [67, 79, 83, 45], "levels": [66, 82, 65, 83]}, "algorithm": 15, "feedback": 1, "oscillator_key_sync": true, "lfo": {"speed": 37, "delay": 0, "pitch_mod_depth": 0, "amp_mod_depth": 0, "key_sync": true, "waveform": "sine"}, "pitch_mod_sensitivity": 3, "transpose": 24, "NAME": "COS-BRAS.Y", "MANUFACTURER": "yamaha", "MODEL": "dx7", "SIGNATURE": "d86a046dc0dcd700d6e7951451d54943a6789375", "AUTHOR": "_Unknown", "BANK": "BRSMISC1.SYX"}