{"operators": [{"envelope_generator": {"rates": [95, 31, 44, 87], "levels": [99, 71, 64, 0]}, "keyboard": {"level_scaling": {"break_point": 0, "left_depth": 0, "left_curve": "-LIN", "right_depth": 0, "right_curve": "-LIN"}, "rate_scaling": 6, "velocity_sensitivity": 1}, "oscillator": {"detune": 0, "frequency": {"fine": 0, "coarse": 0}, "mode": "ratio"}, "amp_mod_sensitivity": 0, "output_level": 97}, {"envelope_generator": {"rates": [97, 58, 65, 21], "levels": [82, 97, 48, 0]}, "keyboard": {"level_scaling": {"break_point": 50, "left_depth": 0, "left_curve": "-LIN", "right_depth": 23, "right_curve": "-LIN"}, "rate_scaling": 5, "velocity_sensitivity": 1}, "oscillator": {"detune": 0, "frequency": {"fine": 0, "coarse": 1}, "mode": "ratio"}, "amp_mod_sensitivity": 0, "output_level": 70}, {"envelope_generator": {"rates": [93, 46, 65, 44], "levels": [97, 38, 52, 46]}, "keyboard": {"level_scaling": {"break_point": 0, "left_depth": 0, "left_curve": "-LIN", "right_depth": 0, "right_curve": "-LIN"}, "rate_scaling": 2, "velocity_sensitivity": 2}, "oscillator": {"detune": 0, "frequency": {"fine": 0, "coarse": 1}, "mode": "ratio"}, "amp_mod_sensitivity": 0, "output_level": 77}, {"envelope_generator": {"rates": [93, 83, 67, 32], "levels": [65, 90, 41, 0]}, "keyboard": {"level_scaling": {"break_point": 0, "left_depth": 0, "left_curve": "-LIN", "right_depth": 0, "right_curve": "-LIN"}, "rate_scaling": 2, "velocity_sensitivity": 0}, "oscillator": {"detune": 0, "frequency": {"fine": 0, "coarse": 6}, "mode": "ratio"}, "amp_mod_sensitivity": 0, "output_level": 65}, {"envelope_generator": {"rates": [95, 98, 53, 24], "levels": [87, 90, 64, 0]}, "keyboard": {"level_scaling": {"break_point": 0, "left_depth": 0, "left_curve": "-LIN", "right_depth": 0, "right_curve": "-LIN"}, "rate_scaling": 2, "velocity_sensitivity": 2}, "oscillator": {"detune": 0, "frequency": {"fine": 0, "coarse": 5}, "mode": "ratio"}, "amp_mod_sensitivity": 0, "output_level": 64}, {"envelope_generator": {"rates": [92, 83, 49, 20], "levels": [50, 90, 71, 0]}, "keyboard": {"level_scaling": {"break_point": 0, "left_depth": 0, "left_curve": "-LIN", "right_depth": 0, "right_curve": "-LIN"}, "rate_scaling": 2, "velocity_sensitivity": 2}, "oscillator": {"detune": 0, "frequency": {"fine": 0, "coarse": 11}, "mode": "ratio"}, "amp_mod_sensitivity": 0, "output_level": 83}], "pitch_envelope_generator": {"rates": [94, 67, 95, 60], "levels": [50, 50, 50, 50]}, "algorithm": 16, "feedback": 6, "oscillator_key_sync": true, "lfo": {"speed": 34, "delay": 33, "pitch_mod_depth": 0, "amp_mod_depth": 0, "key_sync": false, "waveform": "sine"}, "pitch_mod_sensitivity": 1, "transpose": 24, "NAME": "BLOCK.", "MANUFACTURER": "yamaha", "MODEL": "dx7", "SIGNATURE": "650467f1ea1837a61a5eaa4c5b9c1a56ce7eeba6", "AUTHOR": "Yamaha", "BANK": "TX21.SYX"}